persona/__init__.py
persona/client.py
persona/core/__init__.py
persona/core/api_error.py
persona/core/datetime_utils.py
persona/core/jsonable_encoder.py
persona/core/remove_none_from_headers.py
persona/environment.py
persona/errors/__init__.py
persona/errors/bad_request_error.py
persona/errors/conflict_error.py
persona/errors/not_found_error.py
persona/errors/unprocessable_entity_error.py
persona/py.typed
persona/resources/__init__.py
persona/resources/accounts/__init__.py
persona/resources/accounts/client.py
persona/resources/api_keys/__init__.py
persona/resources/api_keys/client.py
persona/resources/api_logs/__init__.py
persona/resources/api_logs/client.py
persona/resources/cases/__init__.py
persona/resources/cases/client.py
persona/resources/database_verifications/__init__.py
persona/resources/database_verifications/client.py
persona/resources/document_verifications/__init__.py
persona/resources/document_verifications/client.py
persona/resources/documents/__init__.py
persona/resources/documents/client.py
persona/resources/email_address_verifications/__init__.py
persona/resources/email_address_verifications/client.py
persona/resources/events/__init__.py
persona/resources/events/client.py
persona/resources/government_id_documents/__init__.py
persona/resources/government_id_documents/client.py
persona/resources/government_id_verifications/__init__.py
persona/resources/government_id_verifications/client.py
persona/resources/graph_queries/__init__.py
persona/resources/graph_queries/client.py
persona/resources/importers/__init__.py
persona/resources/importers/client.py
persona/resources/inquiries/__init__.py
persona/resources/inquiries/client.py
persona/resources/list_items/__init__.py
persona/resources/list_items/client.py
persona/resources/lists/__init__.py
persona/resources/lists/client.py
persona/resources/phone_carrier_database_verifications/__init__.py
persona/resources/phone_carrier_database_verifications/client.py
fern_persona-0.0.4.dist-info/METADATA
fern_persona-0.0.4.dist-info/WHEEL
fern_persona-0.0.4.dist-info/RECORD
